siilo/__init__.py
siilo/_compat.py
siilo/exceptions.py
siilo/storages/__init__.py
siilo/storages/amazon_s3.py
siilo/storages/apache_libcloud.py
siilo/storages/base.py
siilo/storages/filesystem.py
siilo-0.1.0.dist-info/DESCRIPTION.rst
siilo-0.1.0.dist-info/METADATA
siilo-0.1.0.dist-info/metadata.json
siilo-0.1.0.dist-info/RECORD
siilo-0.1.0.dist-info/top_level.txt
siilo-0.1.0.dist-info/WHEEL
