Metadata-Version: 2.0
Name: siilo
Version: 0.1.0
Summary: File storage abstraction layer
Home-page: http://github.com/jpvanhal/siilo
Author: Janne Vanhala
Author-email: janne.vanhala@gmail.com
License: The MIT License (MIT)
